cnvmsg/__init__.py
cnvmsg/constants.py
cnvmsg/enums.py
cnvmsg/errors.py
cnvmsg/models.py
cnvmsg/parsing/__init__.py
cnvmsg/parsing/_block.py
cnvmsg/parsing/_parse.py
cnvmsg/parsing/patterns.py
cnvmsg/parsing/test_composite.py
cnvmsg/parsing/test_single.py
cnvmsg/utils/string.py
cnvmsg-0.1.0.dist-info/METADATA
cnvmsg-0.1.0.dist-info/WHEEL
cnvmsg-0.1.0.dist-info/RECORD
