Metadata-Version: 2.1
Name: cnvmsg
Version: 0.1.0
Summary: Conventional Message handling
Author: ryzhovalex
Author-email: thed4rkof@gmail.com
Requires-Python: >=3.11,<4.0
Classifier: Programming Language :: Python :: 3
Classifier: Programming Language :: Python :: 3.11
Requires-Dist: pydantic (>=1.10.9,<2.0.0)
